aphro/__init__.py
aphro-0.1.1.dist-info/LICENSE
aphro-0.1.1.dist-info/METADATA
aphro-0.1.1.dist-info/WHEEL
aphro-0.1.1.dist-info/top_level.txt
aphro-0.1.1.dist-info/RECORD
