Metadata-Version: 2.1
Name: aphro
Version: 0.1.1
Summary: Python scripting framework for building complex pipelines
Home-page: https://github.com/abhisaini880/Aphro.git
Author: Abhishek Saini
Author-email: abhisaini880@gmail.com
Classifier: Programming Language :: Python :: 3
Classifier: License :: OSI Approved :: GNU General Public License v3 (GPLv3)
Classifier: Operating System :: OS Independent
Requires-Python: >=3.6
License-File: LICENSE
